Workbook

Sheet Lançamentos
A1: Data | B1: Descrição | C1: Categoria | D1: Valor | E1: Pagamento | F1: Anotado por | H1: Linhas amarelas estão sem valor e não entram nos totais. (banri) = Vale-alimentação.

Sheet Resumo
A1: Gastos Casa — resumo por fatura
A2: Cada fatura vai do dia de fechamento (26) ao dia 25 seguinte. Itens sem valor contam só como pendentes.
A4: Fatura (início) | B4: Total | C4: Gastos com valor | D4: Sem valor | E4: Vs. fatura anterior | F4: No vale | G4: Categoria | H4: =A5 | I4: =A6 | J4: =A7 | K4: =A8 | L4: =A9 | M4: =A10 | N4: =A11 | O4: =A12 | P4: =A13 | Q4: =A14 | R4: =A15 | S4: =A16
A5: 46321 | B5: =SUMIFS(Lançamentos!$D$2:$D$1001,Lançamentos!$A$2:$A$1001,">="&A5,Lançamentos!$A$2:$A$1001,"<"&EDATE(A5,1)) | C5: =COUNTIFS(Lançamentos!$A$2:$A$1001,">="&A5,Lançamentos!$A$2:$A$1001,"<"&EDATE(A5,1),Lançamentos!$D$2:$D$1001,"<>") | D5: =COUNTIFS(Lançamentos!$A$2:$A$1001,">="&A5,Lançamentos!$A$2:$A$1001,"<"&EDATE(A5,1),Lançamentos!$D$2:$D$1001,"") | F5: =SUMIFS(Lançamentos!$D$2:$D$1001,Lançamentos!$A$2:$A$1001,">="&A5,Lançamentos!$A$2:$A$1001,"<"&EDATE(A5,1),Lançamentos!$E$2:$E$1001,"Vale-alimentação") | G5: Alimentação | H5: =SUMIFS(Lançamentos!$D$2:$D$1001,Lançamentos!$A$2:$A$1001,">="&H$4,Lançamentos!$A$2:$A$1001,"<"&EDATE(H$4,1),Lançamentos!$C$2:$C$1001,$G5) | I5: =SUMIFS(Lançamentos!$D$2:$D$1001,Lançamentos!$A$2:$A$1001,">="&I$4,Lançamentos!$A$2:$A$1001,"<"&EDATE(I$4,1),Lançamentos!$C$2:$C$1001,$G5) | J5: =SUMIFS(Lançamentos!$D$2:$D$1001,Lançamentos!$A$2:$A$1001,">="&J$4,Lançamentos!$A$2:$A$1001,"<"&EDATE(J$4,1),Lançamentos!$C$2:$C$1001,$G5) | K5: =SUMIFS(Lançamentos!$D$2:$D$1001,Lançamentos!$A$2:$A$1001,">="&K$4,Lançamentos!$A$2:$A$1001,"<"&EDATE(K$4,1),Lançamentos!$C$2:$C$1001,$G5) | L5: =SUMIFS(Lançamentos!$D$2:$D$1001,Lançamentos!$A$2:$A$1001,">="&L$4,Lançamentos!$A$2:$A$1001,"<"&EDATE(L$4,1),Lançamentos!$C$2:$C$1001,$G5) | M5: =SUMIFS(Lançamentos!$D$2:$D$1001,Lançamentos!$A$2:$A$1001,">="&M$4,Lançamentos!$A$2:$A$1001,"<"&EDATE(M$4,1),Lançamentos!$C$2:$C$1001,$G5) | N5: =SUMIFS(Lançamentos!$D$2:$D$1001,Lançamentos!$A$2:$A$1001,">="&N$4,Lançamentos!$A$2:$A$1001,"<"&EDATE(N$4,1),Lançamentos!$C$2:$C$1001,$G5) | O5: =SUMIFS(Lançamentos!$D$2:$D$1001,Lançamentos!$A$2:$A$1001,">="&O$4,Lançamentos!$A$2:$A$1001,"<"&EDATE(O$4,1),Lançamentos!$C$2:$C$1001,$G5) | ... S5: =SUMIFS(Lançamentos!$D$2:$D$1001,Lançamentos!$A$2:$A$1001,">="&S$4,Lançamentos!$A$2:$A$1001,"<"&EDATE(S$4,1),Lançamentos!$C$2:$C$1001,$G5)
A6: =EDATE(A5,1) | B6: =SUMIFS(Lançamentos!$D$2:$D$1001,Lançamentos!$A$2:$A$1001,">="&A6,Lançamentos!$A$2:$A$1001,"<"&EDATE(A6,1)) | C6: =COUNTIFS(Lançamentos!$A$2:$A$1001,">="&A6,Lançamentos!$A$2:$A$1001,"<"&EDATE(A6,1),Lançamentos!$D$2:$D$1001,"<>") | D6: =COUNTIFS(Lançamentos!$A$2:$A$1001,">="&A6,Lançamentos!$A$2:$A$1001,"<"&EDATE(A6,1),Lançamentos!$D$2:$D$1001,"") | E6: =IF(B6=0,"",B6-B5) | F6: =SUMIFS(Lançamentos!$D$2:$D$1001,Lançamentos!$A$2:$A$1001,">="&A6,Lançamentos!$A$2:$A$1001,"<"&EDATE(A6,1),Lançamentos!$E$2:$E$1001,"Vale-alimentação") | G6: Casa/contas | H6: =SUMIFS(Lançamentos!$D$2:$D$1001,Lançamentos!$A$2:$A$1001,">="&H$4,Lançamentos!$A$2:$A$1001,"<"&EDATE(H$4,1),Lançamentos!$C$2:$C$1001,$G6) | I6: =SUMIFS(Lançamentos!$D$2:$D$1001,Lançamentos!$A$2:$A$1001,">="&I$4,Lançamentos!$A$2:$A$1001,"<"&EDATE(I$4,1),Lançamentos!$C$2:$C$1001,$G6) | J6: =SUMIFS(Lançamentos!$D$2:$D$1001,Lançamentos!$A$2:$A$1001,">="&J$4,Lançamentos!$A$2:$A$1001,"<"&EDATE(J$4,1),Lançamentos!$C$2:$C$1001,$G6) | K6: =SUMIFS(Lançamentos!$D$2:$D$1001,Lançamentos!$A$2:$A$1001,">="&K$4,Lançamentos!$A$2:$A$1001,"<"&EDATE(K$4,1),Lançamentos!$C$2:$C$1001,$G6) | L6: =SUMIFS(Lançamentos!$D$2:$D$1001,Lançamentos!$A$2:$A$1001,">="&L$4,Lançamentos!$A$2:$A$1001,"<"&EDATE(L$4,1),Lançamentos!$C$2:$C$1001,$G6) | M6: =SUMIFS(Lançamentos!$D$2:$D$1001,Lançamentos!$A$2:$A$1001,">="&M$4,Lançamentos!$A$2:$A$1001,"<"&EDATE(M$4,1),Lançamentos!$C$2:$C$1001,$G6) | N6: =SUMIFS(Lançamentos!$D$2:$D$1001,Lançamentos!$A$2:$A$1001,">="&N$4,Lançamentos!$A$2:$A$1001,"<"&EDATE(N$4,1),Lançamentos!$C$2:$C$1001,$G6) | O6: =SUMIFS(Lançamentos!$D$2:$D$1001,Lançamentos!$A$2:$A$1001,">="&O$4,Lançamentos!$A$2:$A$1001,"<"&EDATE(O$4,1),Lançamentos!$C$2:$C$1001,$G6) | ... S6: =SUMIFS(Lançamentos!$D$2:$D$1001,Lançamentos!$A$2:$A$1001,">="&S$4,Lançamentos!$A$2:$A$1001,"<"&EDATE(S$4,1),Lançamentos!$C$2:$C$1001,$G6)
A7: =EDATE(A6,1) | B7: =SUMIFS(Lançamentos!$D$2:$D$1001,Lançamentos!$A$2:$A$1001,">="&A7,Lançamentos!$A$2:$A$1001,"<"&EDATE(A7,1)) | C7: =COUNTIFS(Lançamentos!$A$2:$A$1001,">="&A7,Lançamentos!$A$2:$A$1001,"<"&EDATE(A7,1),Lançamentos!$D$2:$D$1001,"<>") | D7: =COUNTIFS(Lançamentos!$A$2:$A$1001,">="&A7,Lançamentos!$A$2:$A$1001,"<"&EDATE(A7,1),Lançamentos!$D$2:$D$1001,"") | E7: =IF(B7=0,"",B7-B6) | F7: =SUMIFS(Lançamentos!$D$2:$D$1001,Lançamentos!$A$2:$A$1001,">="&A7,Lançamentos!$A$2:$A$1001,"<"&EDATE(A7,1),Lançamentos!$E$2:$E$1001,"Vale-alimentação") | G7: Transporte | H7: =SUMIFS(Lançamentos!$D$2:$D$1001,Lançamentos!$A$2:$A$1001,">="&H$4,Lançamentos!$A$2:$A$1001,"<"&EDATE(H$4,1),Lançamentos!$C$2:$C$1001,$G7) | I7: =SUMIFS(Lançamentos!$D$2:$D$1001,Lançamentos!$A$2:$A$1001,">="&I$4,Lançamentos!$A$2:$A$1001,"<"&EDATE(I$4,1),Lançamentos!$C$2:$C$1001,$G7) | J7: =SUMIFS(Lançamentos!$D$2:$D$1001,Lançamentos!$A$2:$A$1001,">="&J$4,Lançamentos!$A$2:$A$1001,"<"&EDATE(J$4,1),Lançamentos!$C$2:$C$1001,$G7) | K7: =SUMIFS(Lançamentos!$D$2:$D$1001,Lançamentos!$A$2:$A$1001,">="&K$4,Lançamentos!$A$2:$A$1001,"<"&EDATE(K$4,1),Lançamentos!$C$2:$C$1001,$G7) | L7: =SUMIFS(Lançamentos!$D$2:$D$1001,Lançamentos!$A$2:$A$1001,">="&L$4,Lançamentos!$A$2:$A$1001,"<"&EDATE(L$4,1),Lançamentos!$C$2:$C$1001,$G7) | M7: =SUMIFS(Lançamentos!$D$2:$D$1001,Lançamentos!$A$2:$A$1001,">="&M$4,Lançamentos!$A$2:$A$1001,"<"&EDATE(M$4,1),Lançamentos!$C$2:$C$1001,$G7) | N7: =SUMIFS(Lançamentos!$D$2:$D$1001,Lançamentos!$A$2:$A$1001,">="&N$4,Lançamentos!$A$2:$A$1001,"<"&EDATE(N$4,1),Lançamentos!$C$2:$C$1001,$G7) | O7: =SUMIFS(Lançamentos!$D$2:$D$1001,Lançamentos!$A$2:$A$1001,">="&O$4,Lançamentos!$A$2:$A$1001,"<"&EDATE(O$4,1),Lançamentos!$C$2:$C$1001,$G7) | ... S7: =SUMIFS(Lançamentos!$D$2:$D$1001,Lançamentos!$A$2:$A$1001,">="&S$4,Lançamentos!$A$2:$A$1001,"<"&EDATE(S$4,1),Lançamentos!$C$2:$C$1001,$G7)
A8: =EDATE(A7,1) | B8: =SUMIFS(Lançamentos!$D$2:$D$1001,Lançamentos!$A$2:$A$1001,">="&A8,Lançamentos!$A$2:$A$1001,"<"&EDATE(A8,1)) | C8: =COUNTIFS(Lançamentos!$A$2:$A$1001,">="&A8,Lançamentos!$A$2:$A$1001,"<"&EDATE(A8,1),Lançamentos!$D$2:$D$1001,"<>") | D8: =COUNTIFS(Lançamentos!$A$2:$A$1001,">="&A8,Lançamentos!$A$2:$A$1001,"<"&EDATE(A8,1),Lançamentos!$D$2:$D$1001,"") | E8: =IF(B8=0,"",B8-B7) | F8: =SUMIFS(Lançamentos!$D$2:$D$1001,Lançamentos!$A$2:$A$1001,">="&A8,Lançamentos!$A$2:$A$1001,"<"&EDATE(A8,1),Lançamentos!$E$2:$E$1001,"Vale-alimentação") | G8: Saúde | H8: =SUMIFS(Lançamentos!$D$2:$D$1001,Lançamentos!$A$2:$A$1001,">="&H$4,Lançamentos!$A$2:$A$1001,"<"&EDATE(H$4,1),Lançamentos!$C$2:$C$1001,$G8) | I8: =SUMIFS(Lançamentos!$D$2:$D$1001,Lançamentos!$A$2:$A$1001,">="&I$4,Lançamentos!$A$2:$A$1001,"<"&EDATE(I$4,1),Lançamentos!$C$2:$C$1001,$G8) | J8: =SUMIFS(Lançamentos!$D$2:$D$1001,Lançamentos!$A$2:$A$1001,">="&J$4,Lançamentos!$A$2:$A$1001,"<"&EDATE(J$4,1),Lançamentos!$C$2:$C$1001,$G8) | K8: =SUMIFS(Lançamentos!$D$2:$D$1001,Lançamentos!$A$2:$A$1001,">="&K$4,Lançamentos!$A$2:$A$1001,"<"&EDATE(K$4,1),Lançamentos!$C$2:$C$1001,$G8) | L8: =SUMIFS(Lançamentos!$D$2:$D$1001,Lançamentos!$A$2:$A$1001,">="&L$4,Lançamentos!$A$2:$A$1001,"<"&EDATE(L$4,1),Lançamentos!$C$2:$C$1001,$G8) | M8: =SUMIFS(Lançamentos!$D$2:$D$1001,Lançamentos!$A$2:$A$1001,">="&M$4,Lançamentos!$A$2:$A$1001,"<"&EDATE(M$4,1),Lançamentos!$C$2:$C$1001,$G8) | N8: =SUMIFS(Lançamentos!$D$2:$D$1001,Lançamentos!$A$2:$A$1001,">="&N$4,Lançamentos!$A$2:$A$1001,"<"&EDATE(N$4,1),Lançamentos!$C$2:$C$1001,$G8) | O8: =SUMIFS(Lançamentos!$D$2:$D$1001,Lançamentos!$A$2:$A$1001,">="&O$4,Lançamentos!$A$2:$A$1001,"<"&EDATE(O$4,1),Lançamentos!$C$2:$C$1001,$G8) | ... S8: =SUMIFS(Lançamentos!$D$2:$D$1001,Lançamentos!$A$2:$A$1001,">="&S$4,Lançamentos!$A$2:$A$1001,"<"&EDATE(S$4,1),Lançamentos!$C$2:$C$1001,$G8)
A9: =EDATE(A8,1) | B9: =SUMIFS(Lançamentos!$D$2:$D$1001,Lançamentos!$A$2:$A$1001,">="&A9,Lançamentos!$A$2:$A$1001,"<"&EDATE(A9,1)) | C9: =COUNTIFS(Lançamentos!$A$2:$A$1001,">="&A9,Lançamentos!$A$2:$A$1001,"<"&EDATE(A9,1),Lançamentos!$D$2:$D$1001,"<>") | D9: =COUNTIFS(Lançamentos!$A$2:$A$1001,">="&A9,Lançamentos!$A$2:$A$1001,"<"&EDATE(A9,1),Lançamentos!$D$2:$D$1001,"") | E9: =IF(B9=0,"",B9-B8) | F9: =SUMIFS(Lançamentos!$D$2:$D$1001,Lançamentos!$A$2:$A$1001,">="&A9,Lançamentos!$A$2:$A$1001,"<"&EDATE(A9,1),Lançamentos!$E$2:$E$1001,"Vale-alimentação") | G9: Lazer | H9: =SUMIFS(Lançamentos!$D$2:$D$1001,Lançamentos!$A$2:$A$1001,">="&H$4,Lançamentos!$A$2:$A$1001,"<"&EDATE(H$4,1),Lançamentos!$C$2:$C$1001,$G9) | I9: =SUMIFS(Lançamentos!$D$2:$D$1001,Lançamentos!$A$2:$A$1001,">="&I$4,Lançamentos!$A$2:$A$1001,"<"&EDATE(I$4,1),Lançamentos!$C$2:$C$1001,$G9) | J9: =SUMIFS(Lançamentos!$D$2:$D$1001,Lançamentos!$A$2:$A$1001,">="&J$4,Lançamentos!$A$2:$A$1001,"<"&EDATE(J$4,1),Lançamentos!$C$2:$C$1001,$G9) | K9: =SUMIFS(Lançamentos!$D$2:$D$1001,Lançamentos!$A$2:$A$1001,">="&K$4,Lançamentos!$A$2:$A$1001,"<"&EDATE(K$4,1),Lançamentos!$C$2:$C$1001,$G9) | L9: =SUMIFS(Lançamentos!$D$2:$D$1001,Lançamentos!$A$2:$A$1001,">="&L$4,Lançamentos!$A$2:$A$1001,"<"&EDATE(L$4,1),Lançamentos!$C$2:$C$1001,$G9) | M9: =SUMIFS(Lançamentos!$D$2:$D$1001,Lançamentos!$A$2:$A$1001,">="&M$4,Lançamentos!$A$2:$A$1001,"<"&EDATE(M$4,1),Lançamentos!$C$2:$C$1001,$G9) | N9: =SUMIFS(Lançamentos!$D$2:$D$1001,Lançamentos!$A$2:$A$1001,">="&N$4,Lançamentos!$A$2:$A$1001,"<"&EDATE(N$4,1),Lançamentos!$C$2:$C$1001,$G9) | O9: =SUMIFS(Lançamentos!$D$2:$D$1001,Lançamentos!$A$2:$A$1001,">="&O$4,Lançamentos!$A$2:$A$1001,"<"&EDATE(O$4,1),Lançamentos!$C$2:$C$1001,$G9) | ... S9: =SUMIFS(Lançamentos!$D$2:$D$1001,Lançamentos!$A$2:$A$1001,">="&S$4,Lançamentos!$A$2:$A$1001,"<"&EDATE(S$4,1),Lançamentos!$C$2:$C$1001,$G9)
A10: =EDATE(A9,1) | B10: =SUMIFS(Lançamentos!$D$2:$D$1001,Lançamentos!$A$2:$A$1001,">="&A10,Lançamentos!$A$2:$A$1001,"<"&EDATE(A10,1)) | C10: =COUNTIFS(Lançamentos!$A$2:$A$1001,">="&A10,Lançamentos!$A$2:$A$1001,"<"&EDATE(A10,1),Lançamentos!$D$2:$D$1001,"<>") | D10: =COUNTIFS(Lançamentos!$A$2:$A$1001,">="&A10,Lançamentos!$A$2:$A$1001,"<"&EDATE(A10,1),Lançamentos!$D$2:$D$1001,"") | E10: =IF(B10=0,"",B10-B9) | F10: =SUMIFS(Lançamentos!$D$2:$D$1001,Lançamentos!$A$2:$A$1001,">="&A10,Lançamentos!$A$2:$A$1001,"<"&EDATE(A10,1),Lançamentos!$E$2:$E$1001,"Vale-alimentação") | G10: Outros | H10: =SUMIFS(Lançamentos!$D$2:$D$1001,Lançamentos!$A$2:$A$1001,">="&H$4,Lançamentos!$A$2:$A$1001,"<"&EDATE(H$4,1),Lançamentos!$C$2:$C$1001,$G10) | I10: =SUMIFS(Lançamentos!$D$2:$D$1001,Lançamentos!$A$2:$A$1001,">="&I$4,Lançamentos!$A$2:$A$1001,"<"&EDATE(I$4,1),Lançamentos!$C$2:$C$1001,$G10) | J10: =SUMIFS(Lançamentos!$D$2:$D$1001,Lançamentos!$A$2:$A$1001,">="&J$4,Lançamentos!$A$2:$A$1001,"<"&EDATE(J$4,1),Lançamentos!$C$2:$C$1001,$G10) | K10: =SUMIFS(Lançamentos!$D$2:$D$1001,Lançamentos!$A$2:$A$1001,">="&K$4,Lançamentos!$A$2:$A$1001,"<"&EDATE(K$4,1),Lançamentos!$C$2:$C$1001,$G10) | L10: =SUMIFS(Lançamentos!$D$2:$D$1001,Lançamentos!$A$2:$A$1001,">="&L$4,Lançamentos!$A$2:$A$1001,"<"&EDATE(L$4,1),Lançamentos!$C$2:$C$1001,$G10) | M10: =SUMIFS(Lançamentos!$D$2:$D$1001,Lançamentos!$A$2:$A$1001,">="&M$4,Lançamentos!$A$2:$A$1001,"<"&EDATE(M$4,1),Lançamentos!$C$2:$C$1001,$G10) | N10: =SUMIFS(Lançamentos!$D$2:$D$1001,Lançamentos!$A$2:$A$1001,">="&N$4,Lançamentos!$A$2:$A$1001,"<"&EDATE(N$4,1),Lançamentos!$C$2:$C$1001,$G10) | O10: =SUMIFS(Lançamentos!$D$2:$D$1001,Lançamentos!$A$2:$A$1001,">="&O$4,Lançamentos!$A$2:$A$1001,"<"&EDATE(O$4,1),Lançamentos!$C$2:$C$1001,$G10) | ... S10: =SUMIFS(Lançamentos!$D$2:$D$1001,Lançamentos!$A$2:$A$1001,">="&S$4,Lançamentos!$A$2:$A$1001,"<"&EDATE(S$4,1),Lançamentos!$C$2:$C$1001,$G10)
A11: =EDATE(A10,1) | B11: =SUMIFS(Lançamentos!$D$2:$D$1001,Lançamentos!$A$2:$A$1001,">="&A11,Lançamentos!$A$2:$A$1001,"<"&EDATE(A11,1)) | C11: =COUNTIFS(Lançamentos!$A$2:$A$1001,">="&A11,Lançamentos!$A$2:$A$1001,"<"&EDATE(A11,1),Lançamentos!$D$2:$D$1001,"<>") | D11: =COUNTIFS(Lançamentos!$A$2:$A$1001,">="&A11,Lançamentos!$A$2:$A$1001,"<"&EDATE(A11,1),Lançamentos!$D$2:$D$1001,"") | E11: =IF(B11=0,"",B11-B10) | F11: =SUMIFS(Lançamentos!$D$2:$D$1001,Lançamentos!$A$2:$A$1001,">="&A11,Lançamentos!$A$2:$A$1001,"<"&EDATE(A11,1),Lançamentos!$E$2:$E$1001,"Vale-alimentação") | G11: Total | H11: =SUM(H5:H10) | I11: =SUM(I5:I10) | J11: =SUM(J5:J10) | K11: =SUM(K5:K10) | L11: =SUM(L5:L10) | M11: =SUM(M5:M10) | N11: =SUM(N5:N10) | O11: =SUM(O5:O10) | ... S11: =SUM(S5:S10)
A12: =EDATE(A11,1) | B12: =SUMIFS(Lançamentos!$D$2:$D$1001,Lançamentos!$A$2:$A$1001,">="&A12,Lançamentos!$A$2:$A$1001,"<"&EDATE(A12,1)) | C12: =COUNTIFS(Lançamentos!$A$2:$A$1001,">="&A12,Lançamentos!$A$2:$A$1001,"<"&EDATE(A12,1),Lançamentos!$D$2:$D$1001,"<>") | D12: =COUNTIFS(Lançamentos!$A$2:$A$1001,">="&A12,Lançamentos!$A$2:$A$1001,"<"&EDATE(A12,1),Lançamentos!$D$2:$D$1001,"") | E12: =IF(B12=0,"",B12-B11) | F12: =SUMIFS(Lançamentos!$D$2:$D$1001,Lançamentos!$A$2:$A$1001,">="&A12,Lançamentos!$A$2:$A$1001,"<"&EDATE(A12,1),Lançamentos!$E$2:$E$1001,"Vale-alimentação")
A13: =EDATE(A12,1) | B13: =SUMIFS(Lançamentos!$D$2:$D$1001,Lançamentos!$A$2:$A$1001,">="&A13,Lançamentos!$A$2:$A$1001,"<"&EDATE(A13,1)) | C13: =COUNTIFS(Lançamentos!$A$2:$A$1001,">="&A13,Lançamentos!$A$2:$A$1001,"<"&EDATE(A13,1),Lançamentos!$D$2:$D$1001,"<>") | D13: =COUNTIFS(Lançamentos!$A$2:$A$1001,">="&A13,Lançamentos!$A$2:$A$1001,"<"&EDATE(A13,1),Lançamentos!$D$2:$D$1001,"") | E13: =IF(B13=0,"",B13-B12) | F13: =SUMIFS(Lançamentos!$D$2:$D$1001,Lançamentos!$A$2:$A$1001,">="&A13,Lançamentos!$A$2:$A$1001,"<"&EDATE(A13,1),Lançamentos!$E$2:$E$1001,"Vale-alimentação") | G13: Fatura atual | H13: =Planejamento!$B$7
A14: =EDATE(A13,1) | B14: =SUMIFS(Lançamentos!$D$2:$D$1001,Lançamentos!$A$2:$A$1001,">="&A14,Lançamentos!$A$2:$A$1001,"<"&EDATE(A14,1)) | C14: =COUNTIFS(Lançamentos!$A$2:$A$1001,">="&A14,Lançamentos!$A$2:$A$1001,"<"&EDATE(A14,1),Lançamentos!$D$2:$D$1001,"<>") | D14: =COUNTIFS(Lançamentos!$A$2:$A$1001,">="&A14,Lançamentos!$A$2:$A$1001,"<"&EDATE(A14,1),Lançamentos!$D$2:$D$1001,"") | E14: =IF(B14=0,"",B14-B13) | F14: =SUMIFS(Lançamentos!$D$2:$D$1001,Lançamentos!$A$2:$A$1001,">="&A14,Lançamentos!$A$2:$A$1001,"<"&EDATE(A14,1),Lançamentos!$E$2:$E$1001,"Vale-alimentação") | G14: =G5 | H14: =INDEX($H5:$S5,MATCH($H$13,$H$4:$S$4,0))
A15: =EDATE(A14,1) | B15: =SUMIFS(Lançamentos!$D$2:$D$1001,Lançamentos!$A$2:$A$1001,">="&A15,Lançamentos!$A$2:$A$1001,"<"&EDATE(A15,1)) | C15: =COUNTIFS(Lançamentos!$A$2:$A$1001,">="&A15,Lançamentos!$A$2:$A$1001,"<"&EDATE(A15,1),Lançamentos!$D$2:$D$1001,"<>") | D15: =COUNTIFS(Lançamentos!$A$2:$A$1001,">="&A15,Lançamentos!$A$2:$A$1001,"<"&EDATE(A15,1),Lançamentos!$D$2:$D$1001,"") | E15: =IF(B15=0,"",B15-B14) | F15: =SUMIFS(Lançamentos!$D$2:$D$1001,Lançamentos!$A$2:$A$1001,">="&A15,Lançamentos!$A$2:$A$1001,"<"&EDATE(A15,1),Lançamentos!$E$2:$E$1001,"Vale-alimentação") | G15: =G6 | H15: =INDEX($H6:$S6,MATCH($H$13,$H$4:$S$4,0))
A16: =EDATE(A15,1) | B16: =SUMIFS(Lançamentos!$D$2:$D$1001,Lançamentos!$A$2:$A$1001,">="&A16,Lançamentos!$A$2:$A$1001,"<"&EDATE(A16,1)) | C16: =COUNTIFS(Lançamentos!$A$2:$A$1001,">="&A16,Lançamentos!$A$2:$A$1001,"<"&EDATE(A16,1),Lançamentos!$D$2:$D$1001,"<>") | D16: =COUNTIFS(Lançamentos!$A$2:$A$1001,">="&A16,Lançamentos!$A$2:$A$1001,"<"&EDATE(A16,1),Lançamentos!$D$2:$D$1001,"") | E16: =IF(B16=0,"",B16-B15) | F16: =SUMIFS(Lançamentos!$D$2:$D$1001,Lançamentos!$A$2:$A$1001,">="&A16,Lançamentos!$A$2:$A$1001,"<"&EDATE(A16,1),Lançamentos!$E$2:$E$1001,"Vale-alimentação") | G16: =G7 | H16: =INDEX($H7:$S7,MATCH($H$13,$H$4:$S$4,0))
G17: =G8 | H17: =INDEX($H8:$S8,MATCH($H$13,$H$4:$S$4,0))
G18: =G9 | H18: =INDEX($H9:$S9,MATCH($H$13,$H$4:$S$4,0))
G19: =G10 | H19: =INDEX($H10:$S10,MATCH($H$13,$H$4:$S$4,0))

Sheet Planejamento
A1: Planejamento futuro
A2: Quanto separar por fatura no ritmo atual. Células amarelas são para vocês editarem.
E3: Gastos fixos mensais fora do grupo
A4: Margem de segurança | B4: 0.1 | E4: Descrição | F4: Valor por mês
A5: Dia de fechamento da fatura | B5: 26
A6: Vale-alimentação por mês
A7: Fatura atual (início) | B7: =IF(COUNT(Lançamentos!$A$2:$A$1001)=0,Resumo!$A$5,DATE(YEAR(MAX(Lançamentos!$A$2:$A$1001)),MONTH(MAX(Lançamentos!$A$2:$A$1001))-IF(DAY(MAX(Lançamentos!$A$2:$A$1001))<B5,1,0),B5))
A8: Fatura atual (fim) | B8: =EDATE(B7,1)-1
A9: Gasto na fatura atual | B9: =SUMIFS(Lançamentos!$D$2:$D$1001,Lançamentos!$A$2:$A$1001,">="&B7,Lançamentos!$A$2:$A$1001,"<="&B8)
A10: Dias com anotações | B10: =IF(COUNT(Lançamentos!$A$2:$A$1001)=0,0,MAX(Lançamentos!$A$2:$A$1001)-B7+1)
A11: Dias na fatura | B11: =B8-B7+1
A12: Média por dia | B12: =IF(B10=0,0,B9/B10)
A13: Projeção da fatura | B13: =B9+B12*(B11-B10)
A14: Faturas anteriores usadas | B14: =COUNTIFS(Resumo!$A$5:$A$16,">="&EDATE(B7,-3),Resumo!$A$5:$A$16,"<"&B7,Resumo!$B$5:$B$16,">0")
A15: Média por fatura (gastos do grupo) | B15: =IF(B14=0,B13,AVERAGEIFS(Resumo!$B$5:$B$16,Resumo!$A$5:$A$16,">="&EDATE(B7,-3),Resumo!$A$5:$A$16,"<"&B7,Resumo!$B$5:$B$16,">0"))
A16: Gastos fixos fora do grupo | B16: =SUM(F5:F24)
A17: Separar por fatura | B17: =(B15+B16)*(1+B4)
A18: Gasto no vale nesta fatura | B18: =SUMIFS(Lançamentos!$D$2:$D$1001,Lançamentos!$A$2:$A$1001,">="&B7,Lançamentos!$A$2:$A$1001,"<="&B8,Lançamentos!$E$2:$E$1001,"Vale-alimentação")
A19: Saldo do vale | B19: =IF(B6="","Preencha o valor do vale",B6-B18)
A21: Reserva por horizonte
A22: Horizonte | B22: Sem margem | C22: Com margem
A23: 1 fatura | B23: =(B$15+B$16)*D23 | C23: =B$17*D23 | D23: 1
A24: 3 faturas | B24: =(B$15+B$16)*D24 | C24: =B$17*D24 | D24: 3
A25: 6 faturas | B25: =(B$15+B$16)*D25 | C25: =B$17*D25 | D25: 6 | E25: Preencham aqui aluguel, condomínio, plano de saúde etc. (ex.: Aluguel | 1.800,00).
A26: 12 faturas | B26: =(B$15+B$16)*D26 | C26: =B$17*D26 | D26: 12
A27: Estimativa fica mais confiável a cada fatura completa anotada.
